[{"toc_title":"System.Web.Services","href":"../../system.web.services","children":[{"toc_title":"WebMethodAttribute","href":"../../system.web.services.webmethodattribute"},{"toc_title":"WebService","href":"../../system.web.services.webservice"},{"toc_title":"WebServiceAttribute","href":"../../system.web.services.webserviceattribute"},{"toc_title":"WebServiceBindingAttribute","href":"../../system.web.services.webservicebindingattribute"},{"toc_title":"WsiProfiles","href":"../../system.web.services.wsiprofiles"}],"pdf_name":"/_splitted/System.Web.Services.pdf"}]