{"author":"dotnet-bot","breadcrumb_path":"breadcrumb/toc.json","search.ms_sitename":"Docs","search.ms_docsetname":"fulldocset","version":null,"locale":"en-us","site_name":"Docs","search.ms_product":"MSDN","depot_name":"MSDN.fulldocset","ref_skeleton_gitcommit":"https://github.com/TianqiZhang/ECMA2YamlTestRepo2/blob/501959ac03e19ac52a27aa4c6bbeb980f8b11c8c/fulldocset/Microsoft.JScript.JSError.yml","original_ref_skeleton_git_url":"https://github.com/TianqiZhang/ECMA2YamlTestRepo2/blob/master/fulldocset/Microsoft.JScript.JSError.yml","open_to_public_contributors":true,"api_name":["Microsoft.JScript.JSError","Microsoft.JScript.JSError.AbstractCannotBePrivate","Microsoft.JScript.JSError.AbstractCannotBeStatic","Microsoft.JScript.JSError.AbstractWithBody","Microsoft.JScript.JSError.ActionNotSupported","Microsoft.JScript.JSError.AmbiguousBindingBecauseOfEval","Microsoft.JScript.JSError.AmbiguousBindingBecauseOfWith","Microsoft.JScript.JSError.AmbiguousConstructorCall","Microsoft.JScript.JSError.AmbiguousMatch","Microsoft.JScript.JSError.ArrayLengthAssignIncorrect","Microsoft.JScript.JSError.ArrayLengthConstructIncorrect","Microsoft.JScript.JSError.ArrayMayBeCopied","Microsoft.JScript.JSError.AssemblyAttributesMustBeGlobal","Microsoft.JScript.JSError.AssignmentToReadOnly","Microsoft.JScript.JSError.BadBreak","Microsoft.JScript.JSError.BadContinue","Microsoft.JScript.JSError.BadFunctionDeclaration","Microsoft.JScript.JSError.BadHexDigit","Microsoft.JScript.JSError.BadLabel","Microsoft.JScript.JSError.BadModifierInInterface","Microsoft.JScript.JSError.BadOctalLiteral","Microsoft.JScript.JSError.BadPropertyDeclaration","Microsoft.JScript.JSError.BadReturn","Microsoft.JScript.JSError.BadSwitch","Microsoft.JScript.JSError.BadThrow","Microsoft.JScript.JSError.BadVariableDeclaration","Microsoft.JScript.JSError.BadWayToLeaveFinally","Microsoft.JScript.JSError.BaseClassIsExpandoAlready","Microsoft.JScript.JSError.BooleanExpected","Microsoft.JScript.JSError.CannotAssignToFunctionResult","Microsoft.JScript.JSError.CannotBeAbstract","Microsoft.JScript.JSError.CannotCallSecurityMethodLateBound","Microsoft.JScript.JSError.CannotChangeVisibility","Microsoft.JScript.JSError.CannotInstantiateAbstractClass","Microsoft.JScript.JSError.CannotNestPositionDirective","Microsoft.JScript.JSError.CannotReturnValueFromVoidFunction","Microsoft.JScript.JSError.CannotUseNameOfClass","Microsoft.JScript.JSError.CannotUseStaticSecurityAttribute","Microsoft.JScript.JSError.CantAssignThis","Microsoft.JScript.JSError.CantCreateObject","Microsoft.JScript.JSError.CcInvalidElif","Microsoft.JScript.JSError.CcInvalidElse","Microsoft.JScript.JSError.CcInvalidEnd","Microsoft.JScript.JSError.CcInvalidInDebugger","Microsoft.JScript.JSError.CcOff","Microsoft.JScript.JSError.CircularDefinition","Microsoft.JScript.JSError.ClashWithProperty","Microsoft.JScript.JSError.ClassNotAllowed","Microsoft.JScript.JSError.ConstructorMayNotHaveReturnType","Microsoft.JScript.JSError.CustomAttributeUsedMoreThanOnce","Microsoft.JScript.JSError.DateExpected","Microsoft.JScript.JSError.DelegatesShouldNotBeExplicitlyConstructed","Microsoft.JScript.JSError.Deprecated","Microsoft.JScript.JSError.DifferentReturnTypeFromBase","Microsoft.JScript.JSError.DoesNotHaveAnAddress","Microsoft.JScript.JSError.DupDefault","Microsoft.JScript.JSError.DuplicateMethod","Microsoft.JScript.JSError.DuplicateName","Microsoft.JScript.JSError.DuplicateNamedParameter","Microsoft.JScript.JSError.DupVisibility","Microsoft.JScript.JSError.EnumeratorExpected","Microsoft.JScript.JSError.EnumNotAllowed","Microsoft.JScript.JSError.ErrEOF","Microsoft.JScript.JSError.ExceptionFromHResult","Microsoft.JScript.JSError.ExecutablesCannotBeLocalized","Microsoft.JScript.JSError.ExpandoClassShouldNotImpleEnumerable","Microsoft.JScript.JSError.ExpandoMustBePublic","Microsoft.JScript.JSError.ExpandoPrecludesAbstract","Microsoft.JScript.JSError.ExpandoPrecludesOverride","Microsoft.JScript.JSError.ExpandoPrecludesStatic","Microsoft.JScript.JSError.ExpectedAssembly","Microsoft.JScript.JSError.ExpressionExpected","Microsoft.JScript.JSError.FileNotFound","Microsoft.JScript.JSError.FinalPrecludesAbstract","Microsoft.JScript.JSError.FractionOutOfRange","Microsoft.JScript.JSError.FuncEvalAborted","Microsoft.JScript.JSError.FuncEvalBadLocation","Microsoft.JScript.JSError.FuncEvalBadThreadNotStarted","Microsoft.JScript.JSError.FuncEvalBadThreadState","Microsoft.JScript.JSError.FuncEvalThreadSleepWaitJoin","Microsoft.JScript.JSError.FuncEvalThreadSuspended","Microsoft.JScript.JSError.FuncEvalTimedout","Microsoft.JScript.JSError.FuncEvalWebMethod","Microsoft.JScript.JSError.FunctionExpected","Microsoft.JScript.JSError.GetAndSetAreInconsistent","Microsoft.JScript.JSError.HidesAbstractInBase","Microsoft.JScript.JSError.HidesParentMember","Microsoft.JScript.JSError.IllegalAssignment","Microsoft.JScript.JSError.IllegalChar","Microsoft.JScript.JSError.IllegalEval","Microsoft.JScript.JSError.IllegalParamArrayAttribute","Microsoft.JScript.JSError.IllegalUseOfSuper","Microsoft.JScript.JSError.IllegalUseOfThis","Microsoft.JScript.JSError.IllegalVisibility","Microsoft.JScript.JSError.ImplicitlyReferencedAssemblyNotFound","Microsoft.JScript.JSError.ImpossibleConversion","Microsoft.JScript.JSError.IncompatibleAssemblyReference","Microsoft.JScript.JSError.IncompatibleVisibility","Microsoft.JScript.JSError.IncorrectNumberOfIndices","Microsoft.JScript.JSError.InstanceNotAccessibleFromStatic","Microsoft.JScript.JSError.InterfaceIllegalInInterface","Microsoft.JScript.JSError.InternalError","Microsoft.JScript.JSError.InvalidAssemblyKeyFile","Microsoft.JScript.JSError.InvalidBaseTypeForEnum","Microsoft.JScript.JSError.InvalidCall","Microsoft.JScript.JSError.InvalidCustomAttribute","Microsoft.JScript.JSError.InvalidCustomAttributeArgument","Microsoft.JScript.JSError.InvalidCustomAttributeClassOrCtor","Microsoft.JScript.JSError.InvalidCustomAttributeTarget","Microsoft.JScript.JSError.InvalidDebugDirective","Microsoft.JScript.JSError.InvalidElse","Microsoft.JScript.JSError.InvalidImport","Microsoft.JScript.JSError.InvalidLanguageOption","Microsoft.JScript.JSError.InvalidPositionDirective","Microsoft.JScript.JSError.InvalidPrototype","Microsoft.JScript.JSError.InvalidResource","Microsoft.JScript.JSError.ItemNotAllowedOnExpandoClass","Microsoft.JScript.JSError.KeywordUsedAsIdentifier","Microsoft.JScript.JSError.MemberInitializerCannotContainFuncExpr","Microsoft.JScript.JSError.MemberTypeCLSCompliantMismatch","Microsoft.JScript.JSError.MethodClashOnExpandoSuperClass","Microsoft.JScript.JSError.MethodInBaseIsNotVirtual","Microsoft.JScript.JSError.MethodNotAllowedOnExpandoClass","Microsoft.JScript.JSError.MissingConstructForAttributes","Microsoft.JScript.JSError.MissingNameParameter","Microsoft.JScript.JSError.MoreNamedParametersThanArguments","Microsoft.JScript.JSError.MustBeEOL","Microsoft.JScript.JSError.MustImplementMethod","Microsoft.JScript.JSError.MustProvideNameForNamedParameter","Microsoft.JScript.JSError.NeedArrayObject","Microsoft.JScript.JSError.NeedCompileTimeConstant","Microsoft.JScript.JSError.NeedInstance","Microsoft.JScript.JSError.NeedInterface","Microsoft.JScript.JSError.NeedObject","Microsoft.JScript.JSError.NeedType","Microsoft.JScript.JSError.NestedInstanceTypeCannotBeExtendedByStatic","Microsoft.JScript.JSError.NewNotSpecifiedInMethodDeclaration","Microsoft.JScript.JSError.NoAt","Microsoft.JScript.JSError.NoCatch","Microsoft.JScript.JSError.NoCcEnd","Microsoft.JScript.JSError.NoColon","Microsoft.JScript.JSError.NoComma","Microsoft.JScript.JSError.NoCommaOrTypeDefinitionError","Microsoft.JScript.JSError.NoCommentEnd","Microsoft.JScript.JSError.NoConstructor","Microsoft.JScript.JSError.NoEqual","Microsoft.JScript.JSError.NoError","Microsoft.JScript.JSError.NoFuncEvalAllowed","Microsoft.JScript.JSError.NoIdentifier","Microsoft.JScript.JSError.NoLabel","Microsoft.JScript.JSError.NoLeftCurly","Microsoft.JScript.JSError.NoLeftParen","Microsoft.JScript.JSError.NoMemberIdentifier","Microsoft.JScript.JSError.NoMethodInBaseToNew","Microsoft.JScript.JSError.NoMethodInBaseToOverride","Microsoft.JScript.JSError.NonCLSCompliantMember","Microsoft.JScript.JSError.NonCLSCompliantType","Microsoft.JScript.JSError.NonClsException","Microsoft.JScript.JSError.NonStaticWithTypeName","Microsoft.JScript.JSError.NonSupportedInDebugger","Microsoft.JScript.JSError.NoRightBracket","Microsoft.JScript.JSError.NoRightBracketOrComma","Microsoft.JScript.JSError.NoRightCurly","Microsoft.JScript.JSError.NoRightParen","Microsoft.JScript.JSError.NoRightParenOrComma","Microsoft.JScript.JSError.NoSemicolon","Microsoft.JScript.JSError.NoSuchMember","Microsoft.JScript.JSError.NoSuchStaticMember","Microsoft.JScript.JSError.NoSuchType","Microsoft.JScript.JSError.NotAccessible","Microsoft.JScript.JSError.NotAllowedInSuperConstructorCall","Microsoft.JScript.JSError.NotAnExpandoFunction","Microsoft.JScript.JSError.NotCollection","Microsoft.JScript.JSError.NotConst","Microsoft.JScript.JSError.NotDeletable","Microsoft.JScript.JSError.NotIndexable","Microsoft.JScript.JSError.NotInsideClass","Microsoft.JScript.JSError.NotMeantToBeCalledDirectly","Microsoft.JScript.JSError.NotOKToCallSuper","Microsoft.JScript.JSError.NotValidForConstructor","Microsoft.JScript.JSError.NotValidVersionString","Microsoft.JScript.JSError.NotYetImplemented","Microsoft.JScript.JSError.NoVarInEnum","Microsoft.JScript.JSError.NoWhile","Microsoft.JScript.JSError.NumberExpected","Microsoft.JScript.JSError.ObjectExpected","Microsoft.JScript.JSError.OctalLiteralsAreDeprecated","Microsoft.JScript.JSError.OLENoPropOrMethod","Microsoft.JScript.JSError.OnlyClassesAllowed","Microsoft.JScript.JSError.OnlyClassesAndPackagesAllowed","Microsoft.JScript.JSError.OutOfMemory","Microsoft.JScript.JSError.OutOfStack","Microsoft.JScript.JSError.OverrideAndHideUsedTogether","Microsoft.JScript.JSError.PackageExpected","Microsoft.JScript.JSError.PackageInWrongContext","Microsoft.JScript.JSError.ParamListNotLast","Microsoft.JScript.JSError.PossibleBadConversion","Microsoft.JScript.JSError.PossibleBadConversionFromString","Microsoft.JScript.JSError.PrecisionOutOfRange","Microsoft.JScript.JSError.PropertyLevelAttributesMustBeOnGetter","Microsoft.JScript.JSError.RefParamsNonSupportedInDebugger","Microsoft.JScript.JSError.RegExpExpected","Microsoft.JScript.JSError.RegExpSyntax","Microsoft.JScript.JSError.ShouldBeAbstract","Microsoft.JScript.JSError.SideEffectsDisallowed","Microsoft.JScript.JSError.StaticIsAlreadyFinal","Microsoft.JScript.JSError.StaticMethodsCannotHide","Microsoft.JScript.JSError.StaticMethodsCannotOverride","Microsoft.JScript.JSError.StaticMissingInStaticInit","Microsoft.JScript.JSError.StaticRequiresTypeName","Microsoft.JScript.JSError.StaticVarNotAvailable","Microsoft.JScript.JSError.StringConcatIsSlow","Microsoft.JScript.JSError.StringExpected","Microsoft.JScript.JSError.SuperClassConstructorNotAccessible","Microsoft.JScript.JSError.SuspectAssignment","Microsoft.JScript.JSError.SuspectLoopCondition","Microsoft.JScript.JSError.SuspectSemicolon","Microsoft.JScript.JSError.SyntaxError","Microsoft.JScript.JSError.TooFewParameters","Microsoft.JScript.JSError.TooManyParameters","Microsoft.JScript.JSError.TooManyTokensSkipped","Microsoft.JScript.JSError.TypeAssemblyCLSCompliantMismatch","Microsoft.JScript.JSError.TypeCannotBeExtended","Microsoft.JScript.JSError.TypeMismatch","Microsoft.JScript.JSError.TypeNameTooLong","Microsoft.JScript.JSError.TypeObjectNotAvailable","Microsoft.JScript.JSError.UncaughtException","Microsoft.JScript.JSError.UndeclaredVariable","Microsoft.JScript.JSError.UndefinedIdentifier","Microsoft.JScript.JSError.UnexpectedSemicolon","Microsoft.JScript.JSError.UnreachableCatch","Microsoft.JScript.JSError.UnterminatedString","Microsoft.JScript.JSError.URIDecodeError","Microsoft.JScript.JSError.URIEncodeError","Microsoft.JScript.JSError.UselessAssignment","Microsoft.JScript.JSError.UselessExpression","Microsoft.JScript.JSError.VariableLeftUninitialized","Microsoft.JScript.JSError.VariableMightBeUnitialized","Microsoft.JScript.JSError.VarIllegalInInterface","Microsoft.JScript.JSError.VBArrayExpected","Microsoft.JScript.JSError.WriteOnlyProperty","Microsoft.JScript.JSError.WrongDirective","Microsoft.JScript.JSError.WrongUseOfAddressOf"],"api_location":["Microsoft.JScript.dll"],"topic_type":["apiref"],"api_type":["Assembly"],"f1_keywords":["Microsoft.JScript.JSError","Microsoft::JScript::JSError","Microsoft.JScript.JSError.AbstractCannotBePrivate","Microsoft::JScript::JSError::AbstractCannotBePrivate","Microsoft.JScript.JSError.AbstractCannotBeStatic","Microsoft::JScript::JSError::AbstractCannotBeStatic","Microsoft.JScript.JSError.AbstractWithBody","Microsoft::JScript::JSError::AbstractWithBody","Microsoft.JScript.JSError.ActionNotSupported","Microsoft::JScript::JSError::ActionNotSupported","Microsoft.JScript.JSError.AmbiguousBindingBecauseOfEval","Microsoft::JScript::JSError::AmbiguousBindingBecauseOfEval","Microsoft.JScript.JSError.AmbiguousBindingBecauseOfWith","Microsoft::JScript::JSError::AmbiguousBindingBecauseOfWith","Microsoft.JScript.JSError.AmbiguousConstructorCall","Microsoft::JScript::JSError::AmbiguousConstructorCall","Microsoft.JScript.JSError.AmbiguousMatch","Microsoft::JScript::JSError::AmbiguousMatch","Microsoft.JScript.JSError.ArrayLengthAssignIncorrect","Microsoft::JScript::JSError::ArrayLengthAssignIncorrect","Microsoft.JScript.JSError.ArrayLengthConstructIncorrect","Microsoft::JScript::JSError::ArrayLengthConstructIncorrect","Microsoft.JScript.JSError.ArrayMayBeCopied","Microsoft::JScript::JSError::ArrayMayBeCopied","Microsoft.JScript.JSError.AssemblyAttributesMustBeGlobal","Microsoft::JScript::JSError::AssemblyAttributesMustBeGlobal","Microsoft.JScript.JSError.AssignmentToReadOnly","Microsoft::JScript::JSError::AssignmentToReadOnly","Microsoft.JScript.JSError.BadBreak","Microsoft::JScript::JSError::BadBreak","Microsoft.JScript.JSError.BadContinue","Microsoft::JScript::JSError::BadContinue","Microsoft.JScript.JSError.BadFunctionDeclaration","Microsoft::JScript::JSError::BadFunctionDeclaration","Microsoft.JScript.JSError.BadHexDigit","Microsoft::JScript::JSError::BadHexDigit","Microsoft.JScript.JSError.BadLabel","Microsoft::JScript::JSError::BadLabel","Microsoft.JScript.JSError.BadModifierInInterface","Microsoft::JScript::JSError::BadModifierInInterface","Microsoft.JScript.JSError.BadOctalLiteral","Microsoft::JScript::JSError::BadOctalLiteral","Microsoft.JScript.JSError.BadPropertyDeclaration","Microsoft::JScript::JSError::BadPropertyDeclaration","Microsoft.JScript.JSError.BadReturn","Microsoft::JScript::JSError::BadReturn","Microsoft.JScript.JSError.BadSwitch","Microsoft::JScript::JSError::BadSwitch","Microsoft.JScript.JSError.BadThrow","Microsoft::JScript::JSError::BadThrow","Microsoft.JScript.JSError.BadVariableDeclaration","Microsoft::JScript::JSError::BadVariableDeclaration","Microsoft.JScript.JSError.BadWayToLeaveFinally","Microsoft::JScript::JSError::BadWayToLeaveFinally","Microsoft.JScript.JSError.BaseClassIsExpandoAlready","Microsoft::JScript::JSError::BaseClassIsExpandoAlready","Microsoft.JScript.JSError.BooleanExpected","Microsoft::JScript::JSError::BooleanExpected","Microsoft.JScript.JSError.CannotAssignToFunctionResult","Microsoft::JScript::JSError::CannotAssignToFunctionResult","Microsoft.JScript.JSError.CannotBeAbstract","Microsoft::JScript::JSError::CannotBeAbstract","Microsoft.JScript.JSError.CannotCallSecurityMethodLateBound","Microsoft::JScript::JSError::CannotCallSecurityMethodLateBound","Microsoft.JScript.JSError.CannotChangeVisibility","Microsoft::JScript::JSError::CannotChangeVisibility","Microsoft.JScript.JSError.CannotInstantiateAbstractClass","Microsoft::JScript::JSError::CannotInstantiateAbstractClass","Microsoft.JScript.JSError.CannotNestPositionDirective","Microsoft::JScript::JSError::CannotNestPositionDirective","Microsoft.JScript.JSError.CannotReturnValueFromVoidFunction","Microsoft::JScript::JSError::CannotReturnValueFromVoidFunction","Microsoft.JScript.JSError.CannotUseNameOfClass","Microsoft::JScript::JSError::CannotUseNameOfClass","Microsoft.JScript.JSError.CannotUseStaticSecurityAttribute","Microsoft::JScript::JSError::CannotUseStaticSecurityAttribute","Microsoft.JScript.JSError.CantAssignThis","Microsoft::JScript::JSError::CantAssignThis","Microsoft.JScript.JSError.CantCreateObject","Microsoft::JScript::JSError::CantCreateObject","Microsoft.JScript.JSError.CcInvalidElif","Microsoft::JScript::JSError::CcInvalidElif","Microsoft.JScript.JSError.CcInvalidElse","Microsoft::JScript::JSError::CcInvalidElse","Microsoft.JScript.JSError.CcInvalidEnd","Microsoft::JScript::JSError::CcInvalidEnd","Microsoft.JScript.JSError.CcInvalidInDebugger","Microsoft::JScript::JSError::CcInvalidInDebugger","Microsoft.JScript.JSError.CcOff","Microsoft::JScript::JSError::CcOff","Microsoft.JScript.JSError.CircularDefinition","Microsoft::JScript::JSError::CircularDefinition","Microsoft.JScript.JSError.ClashWithProperty","Microsoft::JScript::JSError::ClashWithProperty","Microsoft.JScript.JSError.ClassNotAllowed","Microsoft::JScript::JSError::ClassNotAllowed","Microsoft.JScript.JSError.ConstructorMayNotHaveReturnType","Microsoft::JScript::JSError::ConstructorMayNotHaveReturnType","Microsoft.JScript.JSError.CustomAttributeUsedMoreThanOnce","Microsoft::JScript::JSError::CustomAttributeUsedMoreThanOnce","Microsoft.JScript.JSError.DateExpected","Microsoft::JScript::JSError::DateExpected","Microsoft.JScript.JSError.DelegatesShouldNotBeExplicitlyConstructed","Microsoft::JScript::JSError::DelegatesShouldNotBeExplicitlyConstructed","Microsoft.JScript.JSError.Deprecated","Microsoft::JScript::JSError::Deprecated","Microsoft.JScript.JSError.DifferentReturnTypeFromBase","Microsoft::JScript::JSError::DifferentReturnTypeFromBase","Microsoft.JScript.JSError.DoesNotHaveAnAddress","Microsoft::JScript::JSError::DoesNotHaveAnAddress","Microsoft.JScript.JSError.DupDefault","Microsoft::JScript::JSError::DupDefault","Microsoft.JScript.JSError.DuplicateMethod","Microsoft::JScript::JSError::DuplicateMethod","Microsoft.JScript.JSError.DuplicateName","Microsoft::JScript::JSError::DuplicateName","Microsoft.JScript.JSError.DuplicateNamedParameter","Microsoft::JScript::JSError::DuplicateNamedParameter","Microsoft.JScript.JSError.DupVisibility","Microsoft::JScript::JSError::DupVisibility","Microsoft.JScript.JSError.EnumeratorExpected","Microsoft::JScript::JSError::EnumeratorExpected","Microsoft.JScript.JSError.EnumNotAllowed","Microsoft::JScript::JSError::EnumNotAllowed","Microsoft.JScript.JSError.ErrEOF","Microsoft::JScript::JSError::ErrEOF","Microsoft.JScript.JSError.ExceptionFromHResult","Microsoft::JScript::JSError::ExceptionFromHResult","Microsoft.JScript.JSError.ExecutablesCannotBeLocalized","Microsoft::JScript::JSError::ExecutablesCannotBeLocalized","Microsoft.JScript.JSError.ExpandoClassShouldNotImpleEnumerable","Microsoft::JScript::JSError::ExpandoClassShouldNotImpleEnumerable","Microsoft.JScript.JSError.ExpandoMustBePublic","Microsoft::JScript::JSError::ExpandoMustBePublic","Microsoft.JScript.JSError.ExpandoPrecludesAbstract","Microsoft::JScript::JSError::ExpandoPrecludesAbstract","Microsoft.JScript.JSError.ExpandoPrecludesOverride","Microsoft::JScript::JSError::ExpandoPrecludesOverride","Microsoft.JScript.JSError.ExpandoPrecludesStatic","Microsoft::JScript::JSError::ExpandoPrecludesStatic","Microsoft.JScript.JSError.ExpectedAssembly","Microsoft::JScript::JSError::ExpectedAssembly","Microsoft.JScript.JSError.ExpressionExpected","Microsoft::JScript::JSError::ExpressionExpected","Microsoft.JScript.JSError.FileNotFound","Microsoft::JScript::JSError::FileNotFound","Microsoft.JScript.JSError.FinalPrecludesAbstract","Microsoft::JScript::JSError::FinalPrecludesAbstract","Microsoft.JScript.JSError.FractionOutOfRange","Microsoft::JScript::JSError::FractionOutOfRange","Microsoft.JScript.JSError.FuncEvalAborted","Microsoft::JScript::JSError::FuncEvalAborted","Microsoft.JScript.JSError.FuncEvalBadLocation","Microsoft::JScript::JSError::FuncEvalBadLocation","Microsoft.JScript.JSError.FuncEvalBadThreadNotStarted","Microsoft::JScript::JSError::FuncEvalBadThreadNotStarted","Microsoft.JScript.JSError.FuncEvalBadThreadState","Microsoft::JScript::JSError::FuncEvalBadThreadState","Microsoft.JScript.JSError.FuncEvalThreadSleepWaitJoin","Microsoft::JScript::JSError::FuncEvalThreadSleepWaitJoin","Microsoft.JScript.JSError.FuncEvalThreadSuspended","Microsoft::JScript::JSError::FuncEvalThreadSuspended","Microsoft.JScript.JSError.FuncEvalTimedout","Microsoft::JScript::JSError::FuncEvalTimedout","Microsoft.JScript.JSError.FuncEvalWebMethod","Microsoft::JScript::JSError::FuncEvalWebMethod","Microsoft.JScript.JSError.FunctionExpected","Microsoft::JScript::JSError::FunctionExpected","Microsoft.JScript.JSError.GetAndSetAreInconsistent","Microsoft::JScript::JSError::GetAndSetAreInconsistent","Microsoft.JScript.JSError.HidesAbstractInBase","Microsoft::JScript::JSError::HidesAbstractInBase","Microsoft.JScript.JSError.HidesParentMember","Microsoft::JScript::JSError::HidesParentMember","Microsoft.JScript.JSError.IllegalAssignment","Microsoft::JScript::JSError::IllegalAssignment","Microsoft.JScript.JSError.IllegalChar","Microsoft::JScript::JSError::IllegalChar","Microsoft.JScript.JSError.IllegalEval","Microsoft::JScript::JSError::IllegalEval","Microsoft.JScript.JSError.IllegalParamArrayAttribute","Microsoft::JScript::JSError::IllegalParamArrayAttribute","Microsoft.JScript.JSError.IllegalUseOfSuper","Microsoft::JScript::JSError::IllegalUseOfSuper","Microsoft.JScript.JSError.IllegalUseOfThis","Microsoft::JScript::JSError::IllegalUseOfThis","Microsoft.JScript.JSError.IllegalVisibility","Microsoft::JScript::JSError::IllegalVisibility","Microsoft.JScript.JSError.ImplicitlyReferencedAssemblyNotFound","Microsoft::JScript::JSError::ImplicitlyReferencedAssemblyNotFound","Microsoft.JScript.JSError.ImpossibleConversion","Microsoft::JScript::JSError::ImpossibleConversion","Microsoft.JScript.JSError.IncompatibleAssemblyReference","Microsoft::JScript::JSError::IncompatibleAssemblyReference","Microsoft.JScript.JSError.IncompatibleVisibility","Microsoft::JScript::JSError::IncompatibleVisibility","Microsoft.JScript.JSError.IncorrectNumberOfIndices","Microsoft::JScript::JSError::IncorrectNumberOfIndices","Microsoft.JScript.JSError.InstanceNotAccessibleFromStatic","Microsoft::JScript::JSError::InstanceNotAccessibleFromStatic","Microsoft.JScript.JSError.InterfaceIllegalInInterface","Microsoft::JScript::JSError::InterfaceIllegalInInterface","Microsoft.JScript.JSError.InternalError","Microsoft::JScript::JSError::InternalError","Microsoft.JScript.JSError.InvalidAssemblyKeyFile","Microsoft::JScript::JSError::InvalidAssemblyKeyFile","Microsoft.JScript.JSError.InvalidBaseTypeForEnum","Microsoft::JScript::JSError::InvalidBaseTypeForEnum","Microsoft.JScript.JSError.InvalidCall","Microsoft::JScript::JSError::InvalidCall","Microsoft.JScript.JSError.InvalidCustomAttribute","Microsoft::JScript::JSError::InvalidCustomAttribute","Microsoft.JScript.JSError.InvalidCustomAttributeArgument","Microsoft::JScript::JSError::InvalidCustomAttributeArgument","Microsoft.JScript.JSError.InvalidCustomAttributeClassOrCtor","Microsoft::JScript::JSError::InvalidCustomAttributeClassOrCtor","Microsoft.JScript.JSError.InvalidCustomAttributeTarget","Microsoft::JScript::JSError::InvalidCustomAttributeTarget","Microsoft.JScript.JSError.InvalidDebugDirective","Microsoft::JScript::JSError::InvalidDebugDirective","Microsoft.JScript.JSError.InvalidElse","Microsoft::JScript::JSError::InvalidElse","Microsoft.JScript.JSError.InvalidImport","Microsoft::JScript::JSError::InvalidImport","Microsoft.JScript.JSError.InvalidLanguageOption","Microsoft::JScript::JSError::InvalidLanguageOption","Microsoft.JScript.JSError.InvalidPositionDirective","Microsoft::JScript::JSError::InvalidPositionDirective","Microsoft.JScript.JSError.InvalidPrototype","Microsoft::JScript::JSError::InvalidPrototype","Microsoft.JScript.JSError.InvalidResource","Microsoft::JScript::JSError::InvalidResource","Microsoft.JScript.JSError.ItemNotAllowedOnExpandoClass","Microsoft::JScript::JSError::ItemNotAllowedOnExpandoClass","Microsoft.JScript.JSError.KeywordUsedAsIdentifier","Microsoft::JScript::JSError::KeywordUsedAsIdentifier","Microsoft.JScript.JSError.MemberInitializerCannotContainFuncExpr","Microsoft::JScript::JSError::MemberInitializerCannotContainFuncExpr","Microsoft.JScript.JSError.MemberTypeCLSCompliantMismatch","Microsoft::JScript::JSError::MemberTypeCLSCompliantMismatch","Microsoft.JScript.JSError.MethodClashOnExpandoSuperClass","Microsoft::JScript::JSError::MethodClashOnExpandoSuperClass","Microsoft.JScript.JSError.MethodInBaseIsNotVirtual","Microsoft::JScript::JSError::MethodInBaseIsNotVirtual","Microsoft.JScript.JSError.MethodNotAllowedOnExpandoClass","Microsoft::JScript::JSError::MethodNotAllowedOnExpandoClass","Microsoft.JScript.JSError.MissingConstructForAttributes","Microsoft::JScript::JSError::MissingConstructForAttributes","Microsoft.JScript.JSError.MissingNameParameter","Microsoft::JScript::JSError::MissingNameParameter","Microsoft.JScript.JSError.MoreNamedParametersThanArguments","Microsoft::JScript::JSError::MoreNamedParametersThanArguments","Microsoft.JScript.JSError.MustBeEOL","Microsoft::JScript::JSError::MustBeEOL","Microsoft.JScript.JSError.MustImplementMethod","Microsoft::JScript::JSError::MustImplementMethod","Microsoft.JScript.JSError.MustProvideNameForNamedParameter","Microsoft::JScript::JSError::MustProvideNameForNamedParameter","Microsoft.JScript.JSError.NeedArrayObject","Microsoft::JScript::JSError::NeedArrayObject","Microsoft.JScript.JSError.NeedCompileTimeConstant","Microsoft::JScript::JSError::NeedCompileTimeConstant","Microsoft.JScript.JSError.NeedInstance","Microsoft::JScript::JSError::NeedInstance","Microsoft.JScript.JSError.NeedInterface","Microsoft::JScript::JSError::NeedInterface","Microsoft.JScript.JSError.NeedObject","Microsoft::JScript::JSError::NeedObject","Microsoft.JScript.JSError.NeedType","Microsoft::JScript::JSError::NeedType","Microsoft.JScript.JSError.NestedInstanceTypeCannotBeExtendedByStatic","Microsoft::JScript::JSError::NestedInstanceTypeCannotBeExtendedByStatic","Microsoft.JScript.JSError.NewNotSpecifiedInMethodDeclaration","Microsoft::JScript::JSError::NewNotSpecifiedInMethodDeclaration","Microsoft.JScript.JSError.NoAt","Microsoft::JScript::JSError::NoAt","Microsoft.JScript.JSError.NoCatch","Microsoft::JScript::JSError::NoCatch","Microsoft.JScript.JSError.NoCcEnd","Microsoft::JScript::JSError::NoCcEnd","Microsoft.JScript.JSError.NoColon","Microsoft::JScript::JSError::NoColon","Microsoft.JScript.JSError.NoComma","Microsoft::JScript::JSError::NoComma","Microsoft.JScript.JSError.NoCommaOrTypeDefinitionError","Microsoft::JScript::JSError::NoCommaOrTypeDefinitionError","Microsoft.JScript.JSError.NoCommentEnd","Microsoft::JScript::JSError::NoCommentEnd","Microsoft.JScript.JSError.NoConstructor","Microsoft::JScript::JSError::NoConstructor","Microsoft.JScript.JSError.NoEqual","Microsoft::JScript::JSError::NoEqual","Microsoft.JScript.JSError.NoError","Microsoft::JScript::JSError::NoError","Microsoft.JScript.JSError.NoFuncEvalAllowed","Microsoft::JScript::JSError::NoFuncEvalAllowed","Microsoft.JScript.JSError.NoIdentifier","Microsoft::JScript::JSError::NoIdentifier","Microsoft.JScript.JSError.NoLabel","Microsoft::JScript::JSError::NoLabel","Microsoft.JScript.JSError.NoLeftCurly","Microsoft::JScript::JSError::NoLeftCurly","Microsoft.JScript.JSError.NoLeftParen","Microsoft::JScript::JSError::NoLeftParen","Microsoft.JScript.JSError.NoMemberIdentifier","Microsoft::JScript::JSError::NoMemberIdentifier","Microsoft.JScript.JSError.NoMethodInBaseToNew","Microsoft::JScript::JSError::NoMethodInBaseToNew","Microsoft.JScript.JSError.NoMethodInBaseToOverride","Microsoft::JScript::JSError::NoMethodInBaseToOverride","Microsoft.JScript.JSError.NonCLSCompliantMember","Microsoft::JScript::JSError::NonCLSCompliantMember","Microsoft.JScript.JSError.NonCLSCompliantType","Microsoft::JScript::JSError::NonCLSCompliantType","Microsoft.JScript.JSError.NonClsException","Microsoft::JScript::JSError::NonClsException","Microsoft.JScript.JSError.NonStaticWithTypeName","Microsoft::JScript::JSError::NonStaticWithTypeName","Microsoft.JScript.JSError.NonSupportedInDebugger","Microsoft::JScript::JSError::NonSupportedInDebugger","Microsoft.JScript.JSError.NoRightBracket","Microsoft::JScript::JSError::NoRightBracket","Microsoft.JScript.JSError.NoRightBracketOrComma","Microsoft::JScript::JSError::NoRightBracketOrComma","Microsoft.JScript.JSError.NoRightCurly","Microsoft::JScript::JSError::NoRightCurly","Microsoft.JScript.JSError.NoRightParen","Microsoft::JScript::JSError::NoRightParen","Microsoft.JScript.JSError.NoRightParenOrComma","Microsoft::JScript::JSError::NoRightParenOrComma","Microsoft.JScript.JSError.NoSemicolon","Microsoft::JScript::JSError::NoSemicolon","Microsoft.JScript.JSError.NoSuchMember","Microsoft::JScript::JSError::NoSuchMember","Microsoft.JScript.JSError.NoSuchStaticMember","Microsoft::JScript::JSError::NoSuchStaticMember","Microsoft.JScript.JSError.NoSuchType","Microsoft::JScript::JSError::NoSuchType","Microsoft.JScript.JSError.NotAccessible","Microsoft::JScript::JSError::NotAccessible","Microsoft.JScript.JSError.NotAllowedInSuperConstructorCall","Microsoft::JScript::JSError::NotAllowedInSuperConstructorCall","Microsoft.JScript.JSError.NotAnExpandoFunction","Microsoft::JScript::JSError::NotAnExpandoFunction","Microsoft.JScript.JSError.NotCollection","Microsoft::JScript::JSError::NotCollection","Microsoft.JScript.JSError.NotConst","Microsoft::JScript::JSError::NotConst","Microsoft.JScript.JSError.NotDeletable","Microsoft::JScript::JSError::NotDeletable","Microsoft.JScript.JSError.NotIndexable","Microsoft::JScript::JSError::NotIndexable","Microsoft.JScript.JSError.NotInsideClass","Microsoft::JScript::JSError::NotInsideClass","Microsoft.JScript.JSError.NotMeantToBeCalledDirectly","Microsoft::JScript::JSError::NotMeantToBeCalledDirectly","Microsoft.JScript.JSError.NotOKToCallSuper","Microsoft::JScript::JSError::NotOKToCallSuper","Microsoft.JScript.JSError.NotValidForConstructor","Microsoft::JScript::JSError::NotValidForConstructor","Microsoft.JScript.JSError.NotValidVersionString","Microsoft::JScript::JSError::NotValidVersionString","Microsoft.JScript.JSError.NotYetImplemented","Microsoft::JScript::JSError::NotYetImplemented","Microsoft.JScript.JSError.NoVarInEnum","Microsoft::JScript::JSError::NoVarInEnum","Microsoft.JScript.JSError.NoWhile","Microsoft::JScript::JSError::NoWhile","Microsoft.JScript.JSError.NumberExpected","Microsoft::JScript::JSError::NumberExpected","Microsoft.JScript.JSError.ObjectExpected","Microsoft::JScript::JSError::ObjectExpected","Microsoft.JScript.JSError.OctalLiteralsAreDeprecated","Microsoft::JScript::JSError::OctalLiteralsAreDeprecated","Microsoft.JScript.JSError.OLENoPropOrMethod","Microsoft::JScript::JSError::OLENoPropOrMethod","Microsoft.JScript.JSError.OnlyClassesAllowed","Microsoft::JScript::JSError::OnlyClassesAllowed","Microsoft.JScript.JSError.OnlyClassesAndPackagesAllowed","Microsoft::JScript::JSError::OnlyClassesAndPackagesAllowed","Microsoft.JScript.JSError.OutOfMemory","Microsoft::JScript::JSError::OutOfMemory","Microsoft.JScript.JSError.OutOfStack","Microsoft::JScript::JSError::OutOfStack","Microsoft.JScript.JSError.OverrideAndHideUsedTogether","Microsoft::JScript::JSError::OverrideAndHideUsedTogether","Microsoft.JScript.JSError.PackageExpected","Microsoft::JScript::JSError::PackageExpected","Microsoft.JScript.JSError.PackageInWrongContext","Microsoft::JScript::JSError::PackageInWrongContext","Microsoft.JScript.JSError.ParamListNotLast","Microsoft::JScript::JSError::ParamListNotLast","Microsoft.JScript.JSError.PossibleBadConversion","Microsoft::JScript::JSError::PossibleBadConversion","Microsoft.JScript.JSError.PossibleBadConversionFromString","Microsoft::JScript::JSError::PossibleBadConversionFromString","Microsoft.JScript.JSError.PrecisionOutOfRange","Microsoft::JScript::JSError::PrecisionOutOfRange","Microsoft.JScript.JSError.PropertyLevelAttributesMustBeOnGetter","Microsoft::JScript::JSError::PropertyLevelAttributesMustBeOnGetter","Microsoft.JScript.JSError.RefParamsNonSupportedInDebugger","Microsoft::JScript::JSError::RefParamsNonSupportedInDebugger","Microsoft.JScript.JSError.RegExpExpected","Microsoft::JScript::JSError::RegExpExpected","Microsoft.JScript.JSError.RegExpSyntax","Microsoft::JScript::JSError::RegExpSyntax","Microsoft.JScript.JSError.ShouldBeAbstract","Microsoft::JScript::JSError::ShouldBeAbstract","Microsoft.JScript.JSError.SideEffectsDisallowed","Microsoft::JScript::JSError::SideEffectsDisallowed","Microsoft.JScript.JSError.StaticIsAlreadyFinal","Microsoft::JScript::JSError::StaticIsAlreadyFinal","Microsoft.JScript.JSError.StaticMethodsCannotHide","Microsoft::JScript::JSError::StaticMethodsCannotHide","Microsoft.JScript.JSError.StaticMethodsCannotOverride","Microsoft::JScript::JSError::StaticMethodsCannotOverride","Microsoft.JScript.JSError.StaticMissingInStaticInit","Microsoft::JScript::JSError::StaticMissingInStaticInit","Microsoft.JScript.JSError.StaticRequiresTypeName","Microsoft::JScript::JSError::StaticRequiresTypeName","Microsoft.JScript.JSError.StaticVarNotAvailable","Microsoft::JScript::JSError::StaticVarNotAvailable","Microsoft.JScript.JSError.StringConcatIsSlow","Microsoft::JScript::JSError::StringConcatIsSlow","Microsoft.JScript.JSError.StringExpected","Microsoft::JScript::JSError::StringExpected","Microsoft.JScript.JSError.SuperClassConstructorNotAccessible","Microsoft::JScript::JSError::SuperClassConstructorNotAccessible","Microsoft.JScript.JSError.SuspectAssignment","Microsoft::JScript::JSError::SuspectAssignment","Microsoft.JScript.JSError.SuspectLoopCondition","Microsoft::JScript::JSError::SuspectLoopCondition","Microsoft.JScript.JSError.SuspectSemicolon","Microsoft::JScript::JSError::SuspectSemicolon","Microsoft.JScript.JSError.SyntaxError","Microsoft::JScript::JSError::SyntaxError","Microsoft.JScript.JSError.TooFewParameters","Microsoft::JScript::JSError::TooFewParameters","Microsoft.JScript.JSError.TooManyParameters","Microsoft::JScript::JSError::TooManyParameters","Microsoft.JScript.JSError.TooManyTokensSkipped","Microsoft::JScript::JSError::TooManyTokensSkipped","Microsoft.JScript.JSError.TypeAssemblyCLSCompliantMismatch","Microsoft::JScript::JSError::TypeAssemblyCLSCompliantMismatch","Microsoft.JScript.JSError.TypeCannotBeExtended","Microsoft::JScript::JSError::TypeCannotBeExtended","Microsoft.JScript.JSError.TypeMismatch","Microsoft::JScript::JSError::TypeMismatch","Microsoft.JScript.JSError.TypeNameTooLong","Microsoft::JScript::JSError::TypeNameTooLong","Microsoft.JScript.JSError.TypeObjectNotAvailable","Microsoft::JScript::JSError::TypeObjectNotAvailable","Microsoft.JScript.JSError.UncaughtException","Microsoft::JScript::JSError::UncaughtException","Microsoft.JScript.JSError.UndeclaredVariable","Microsoft::JScript::JSError::UndeclaredVariable","Microsoft.JScript.JSError.UndefinedIdentifier","Microsoft::JScript::JSError::UndefinedIdentifier","Microsoft.JScript.JSError.UnexpectedSemicolon","Microsoft::JScript::JSError::UnexpectedSemicolon","Microsoft.JScript.JSError.UnreachableCatch","Microsoft::JScript::JSError::UnreachableCatch","Microsoft.JScript.JSError.UnterminatedString","Microsoft::JScript::JSError::UnterminatedString","Microsoft.JScript.JSError.URIDecodeError","Microsoft::JScript::JSError::URIDecodeError","Microsoft.JScript.JSError.URIEncodeError","Microsoft::JScript::JSError::URIEncodeError","Microsoft.JScript.JSError.UselessAssignment","Microsoft::JScript::JSError::UselessAssignment","Microsoft.JScript.JSError.UselessExpression","Microsoft::JScript::JSError::UselessExpression","Microsoft.JScript.JSError.VariableLeftUninitialized","Microsoft::JScript::JSError::VariableLeftUninitialized","Microsoft.JScript.JSError.VariableMightBeUnitialized","Microsoft::JScript::JSError::VariableMightBeUnitialized","Microsoft.JScript.JSError.VarIllegalInInterface","Microsoft::JScript::JSError::VarIllegalInInterface","Microsoft.JScript.JSError.VBArrayExpected","Microsoft::JScript::JSError::VBArrayExpected","Microsoft.JScript.JSError.WriteOnlyProperty","Microsoft::JScript::JSError::WriteOnlyProperty","Microsoft.JScript.JSError.WrongDirective","Microsoft::JScript::JSError::WrongDirective","Microsoft.JScript.JSError.WrongUseOfAddressOf","Microsoft::JScript::JSError::WrongUseOfAddressOf"],"dev_langs":["csharp"],"updated_at":"2017-03-01 01:37 AM","document_id":"9af2fa9b-065c-7140-e3a5-a4fc030e8bd0","content_git_url":"https://github.com/TianqiZhang/ECMA2YamlTestRepo2/blob/master/fulldocset/xml/Microsoft.JScript/JSError.xml","layout":"Reference","pagetype":"Reference","title":"JSError enum | Microsoft Docs","description":"Specifies the JScript error messages. This class belongs to the compilation and run-time state category.\n","toc_asset_id":"_splitted/Microsoft.JScript/toc.json","toc_rel":"_splitted/Microsoft.JScript/toc.json","source_url":"","ms.assetid":"Microsoft.JScript.JSError","canonical_url":"https://ppe.docs.microsoft.com/en-us/mergedepotdynamic/microsoft.jscript.jserror","is_dynamic_rendering":true,"content_type":"application/json","publish_version":"{\"opbuild.templates.docs\":\"1.30.0-alpha-006-g4755e46\",\"commit_id\":\"2d9d5470bd6ded1ca54cf84dd0bdd43fce7970f9\",\"branch\":\"master\",\"opbuild.scripts\":\"1.30.0-alpha-006-g4755e46\",\"opbuild.htmltopdftool\":\"1.30.0-alpha-006-g4755e46\",\"opbuild.gitcontributorinformationresolver\":\"1.30.0-alpha-006-g4755e46\",\"opbuild_service\":\"1.30.6.0\",\"docfx.console\":\"2.14.1\",\"opbuild.resolvedependencyconsole\":\"1.30.0-alpha-006-g4755e46\",\"opbuild.schemavalidationconsole\":\"1.30.0-alpha-006-g4755e46\",\"opbuild.redirectionresolver\":\"1.30.0-alpha-006-g4755e46\",\"opbuild.templates.intellisense\":\"1.30.0-alpha-006-g4755e46\",\"dependencies\":[{\"branch\":\"preview\",\"path\":\"_themes\",\"url\":\"https://github.com/Microsoft/templates.docs.msft\",\"commit_id\":\"2fdb10106a8a832b53b99ce357dee0c8dba6389a\",\"opbuild.templates.common\":\"1.29.1\"}]}"}