{"breadcrumb_path":"breadcrumb/toc.json","search.ms_sitename":"Docs","search.ms_docsetname":"fulldocset","version":null,"locale":"en-us","site_name":"Docs","search.ms_product":"MSDN","depot_name":"MSDN.fulldocset","ref_skeleton_gitcommit":"https://github.com/TianqiZhang/ECMA2YamlTestRepo2/blob/501959ac03e19ac52a27aa4c6bbeb980f8b11c8c/fulldocset/System.Web.UI.WebControls.ControlParameter.yml","original_ref_skeleton_git_url":"https://github.com/TianqiZhang/ECMA2YamlTestRepo2/blob/master/fulldocset/System.Web.UI.WebControls.ControlParameter.yml","open_to_public_contributors":true,"api_name":["System.Web.UI.WebControls.ControlParameter","System.Web.UI.WebControls.ControlParameter..ctor","System.Web.UI.WebControls.ControlParameter.Clone","System.Web.UI.WebControls.ControlParameter.ControlID","System.Web.UI.WebControls.ControlParameter.Evaluate","System.Web.UI.WebControls.ControlParameter.PropertyName"],"api_location":["System.Web.dll"],"topic_type":["apiref"],"api_type":["Assembly"],"f1_keywords":["System.Web.UI.WebControls.ControlParameter","System::Web::UI::WebControls::ControlParameter","System.Web.UI.WebControls.ControlParameter.#ctor","System::Web::UI::WebControls::ControlParameter::#ctor","System.Web.UI.WebControls.ControlParameter.Clone","System::Web::UI::WebControls::ControlParameter::Clone","System.Web.UI.WebControls.ControlParameter.ControlID","System::Web::UI::WebControls::ControlParameter::ControlID","System.Web.UI.WebControls.ControlParameter.Evaluate","System::Web::UI::WebControls::ControlParameter::Evaluate","System.Web.UI.WebControls.ControlParameter.PropertyName","System::Web::UI::WebControls::ControlParameter::PropertyName"],"dev_langs":["csharp"],"updated_at":"2017-03-01 01:37 AM","document_id":"7e07ff75-2ac4-c82f-d3f9-daf986f9736e","original_ecmaxml_local_path":"W:\\o2y0\\s\\fulldocset\\xml\\System.Web.UI.WebControls\\ControlParameter.xml","content_git_url":"https://github.com/TianqiZhang/ECMA2YamlTestRepo2/blob/master/fulldocset/xml/System.Web.UI.WebControls/ControlParameter.xml","layout":"Reference","pagetype":"Reference","title":"ControlParameter class | Microsoft Docs","description":"Binds the value of a property of a  to a parameter object.\n","toc_asset_id":"_splitted/System.Web.UI.WebControls/toc.json","toc_rel":"_splitted/System.Web.UI.WebControls/toc.json","source_url":"","ms.assetid":"System.Web.UI.WebControls.ControlParameter","canonical_url":"https://ppe.docs.microsoft.com/en-us/mergedepotdynamic/system.web.ui.webcontrols.controlparameter","is_dynamic_rendering":true,"content_type":"application/json","publish_version":"{\"opbuild.templates.docs\":\"1.29.0-alpha-035-gc8b05e8\",\"commit_id\":\"d2c9a7d1bd432ea3ad9c844e57fa835a339f6bed\",\"branch\":\"master\",\"opbuild.scripts\":\"1.29.0-alpha-035-gc8b05e8\",\"opbuild.htmltopdftool\":\"1.29.0-alpha-035-gc8b05e8\",\"opbuild.gitcontributorinformationresolver\":\"1.29.0-alpha-035-gc8b05e8\",\"opbuild_service\":\"1.29.35.0\",\"docfx.console\":\"2.14.0-alpha-1281-g4ed538b\",\"opbuild.resolvedependencyconsole\":\"1.29.0-alpha-035-gc8b05e8\",\"opbuild.schemavalidationconsole\":\"1.29.0-alpha-035-gc8b05e8\",\"opbuild.redirectionresolver\":\"1.29.0-alpha-035-gc8b05e8\",\"opbuild.templates.intellisense\":\"1.29.0-alpha-035-gc8b05e8\",\"dependencies\":[{\"branch\":\"master\",\"path\":\"_themes\",\"url\":\"https://github.com/Microsoft/templates.docs.msft\",\"commit_id\":\"7d3ef1a51554bb393cfbe59160c498316c9c2dc3\",\"opbuild.templates.common\":\"1.29.0-alpha-035-gc8b05e8\"}]}"}