{"author":"dotnet-bot","breadcrumb_path":"breadcrumb/toc.json","search.ms_sitename":"Docs","search.ms_docsetname":"fulldocset","version":null,"locale":"en-us","site_name":"Docs","search.ms_product":"MSDN","depot_name":"MSDN.fulldocset","ref_skeleton_gitcommit":"https://github.com/TianqiZhang/ECMA2YamlTestRepo2/blob/417c04fd1daf0cb211ec4909020356fc1fe69260/fulldocset/System.ServiceModel.BasicHttpsSecurityMode.yml","original_ref_skeleton_git_url":"https://github.com/TianqiZhang/ECMA2YamlTestRepo2/blob/master/fulldocset/System.ServiceModel.BasicHttpsSecurityMode.yml","open_to_public_contributors":true,"api_name":["System.ServiceModel.BasicHttpsSecurityMode","System.ServiceModel.BasicHttpsSecurityMode.Transport","System.ServiceModel.BasicHttpsSecurityMode.TransportWithMessageCredential"],"api_location":["System.ServiceModel.dll"],"topic_type":["apiref"],"api_type":["Assembly"],"f1_keywords":["System.ServiceModel.BasicHttpsSecurityMode","System::ServiceModel::BasicHttpsSecurityMode","System.ServiceModel.BasicHttpsSecurityMode.Transport","System::ServiceModel::BasicHttpsSecurityMode::Transport","System.ServiceModel.BasicHttpsSecurityMode.TransportWithMessageCredential","System::ServiceModel::BasicHttpsSecurityMode::TransportWithMessageCredential"],"dev_langs":["csharp"],"updated_at":"2017-02-28 06:06 AM","document_id":"70f5d9aa-1491-6ceb-9b53-e815a396e8ca","content_git_url":"https://github.com/TianqiZhang/ECMA2YamlTestRepo2/blob/master/fulldocset/xml/System.ServiceModel/BasicHttpsSecurityMode.xml","layout":"Reference","pagetype":"Reference","title":"BasicHttpsSecurityMode enum | Microsoft Docs","description":"Specifies the basic https security mode.\n","toc_asset_id":"_splitted/System.ServiceModel/toc.json","toc_rel":"_splitted/System.ServiceModel/toc.json","source_url":"","ms.assetid":"System.ServiceModel.BasicHttpsSecurityMode","canonical_url":"https://ppe.docs.microsoft.com/en-us/mergedepotdynamic/system.servicemodel.basichttpssecuritymode","is_dynamic_rendering":true,"content_type":"application/json","publish_version":"{\"opbuild.templates.docs\":\"1.29.0-alpha-081-gadbd21c\",\"commit_id\":\"f7ad7ac9b65baa8d9d931a7ded612d5e7a5d9bd6\",\"branch\":\"master\",\"opbuild.scripts\":\"1.29.0-alpha-081-gadbd21c\",\"opbuild.htmltopdftool\":\"1.29.0-alpha-081-gadbd21c\",\"opbuild.gitcontributorinformationresolver\":\"1.29.0-alpha-081-gadbd21c\",\"opbuild_service\":\"1.29.81.0\",\"docfx.console\":\"2.14.0-alpha-1315-gafbcc26\",\"opbuild.resolvedependencyconsole\":\"1.29.0-alpha-081-gadbd21c\",\"opbuild.schemavalidationconsole\":\"1.29.0-alpha-081-gadbd21c\",\"opbuild.redirectionresolver\":\"1.29.0-alpha-081-gadbd21c\",\"opbuild.templates.intellisense\":\"1.29.0-alpha-081-gadbd21c\",\"dependencies\":[{\"branch\":\"master\",\"path\":\"_themes\",\"url\":\"https://github.com/Microsoft/templates.docs.msft\",\"commit_id\":\"e9df56b7a82b3d69f77c29be325ce20965f94445\",\"opbuild.templates.common\":\"1.29.0-alpha-081-gadbd21c\"}]}"}